tk_de_common/__init__.py
tk_de_common/hasher.py
tk_de_common/s3_util.py
tk_de_common-3.2.1.dist-info/LICENSE
tk_de_common-3.2.1.dist-info/METADATA
tk_de_common-3.2.1.dist-info/WHEEL
tk_de_common-3.2.1.dist-info/top_level.txt
tk_de_common-3.2.1.dist-info/RECORD
