Metadata-Version: 2.1
Name: tk-de-common
Version: 3.2.1
Summary: Wrappers for some common data engineering apis
Home-page: https://github.com/terakeet/pypi-tk-de-common
Author: Innovation Team
Author-email: innovation@terakeet.com
Project-URL: Bug Tracker, https://github.com/terakeet/pypi-tk-de-common/issues
Classifier: Programming Language :: Python :: 3
Classifier: License :: OSI Approved :: MIT License
Classifier: Operating System :: OS Independent
Requires-Python: >=3.8
License-File: LICENSE
Requires-Dist: python-dotenv (>=0.21.1)
Provides-Extra: test
Requires-Dist: pytest ; extra == 'test'
Requires-Dist: flake8 ; extra == 'test'
